rer.externalnews-1.1.1-py3.10-nspkg.pth
rer/externalnews/__init__.py
rer/externalnews/configure.zcml
rer/externalnews/indexers.py
rer/externalnews/interfaces.py
rer/externalnews/setuphandlers.py
rer/externalnews/testing.py
rer/externalnews/browser/__init__.py
rer/externalnews/browser/configure.zcml
rer/externalnews/browser/externalnews_view.py
rer/externalnews/browser/restapi/__init__.py
rer/externalnews/browser/restapi/configure.zcml
rer/externalnews/browser/restapi/serializers/__init__.py
rer/externalnews/browser/restapi/serializers/configure.zcml
rer/externalnews/browser/restapi/serializers/externalnews.py
rer/externalnews/browser/templates/externalnews.pt
rer/externalnews/locales/rer.externalnews.pot
rer/externalnews/locales/update.sh
rer/externalnews/locales/it/LC_MESSAGES/rer.externalnews.mo
rer/externalnews/locales/it/LC_MESSAGES/rer.externalnews.po
rer/externalnews/locales/it/LC_MESSAGES/rer.externalnews.pot
rer/externalnews/profiles/default/browserlayer.xml
rer/externalnews/profiles/default/catalog.xml
rer/externalnews/profiles/default/diff_tool.xml
rer/externalnews/profiles/default/metadata.xml
rer/externalnews/profiles/default/registry.xml
rer/externalnews/profiles/default/repositorytool.xml
rer/externalnews/profiles/default/types.xml
rer/externalnews/profiles/default/types/ExternalNews.xml
rer/externalnews/profiles/uninstall/browserlayer.xml
rer/externalnews/tests/__init__.py
rer/externalnews/tests/test_externalnews.py
rer/externalnews/upgrades/__init__.py
rer/externalnews/upgrades/configure.zcml
rer/externalnews/upgrades/upgrades.py
rer.externalnews-1.1.1.dist-info/LICENSE.GPL
rer.externalnews-1.1.1.dist-info/LICENSE.rst
rer.externalnews-1.1.1.dist-info/METADATA
rer.externalnews-1.1.1.dist-info/WHEEL
rer.externalnews-1.1.1.dist-info/entry_points.txt
rer.externalnews-1.1.1.dist-info/namespace_packages.txt
rer.externalnews-1.1.1.dist-info/top_level.txt
rer.externalnews-1.1.1.dist-info/RECORD
